setup.py
eba_binomial/Binomialdistribution.py
eba_binomial/Gaussiandistribution.py
eba_binomial/Generaldistribution.py
eba_binomial/__init__.py
eba_binomial.egg-info/PKG-INFO
eba_binomial.egg-info/SOURCES.txt
eba_binomial.egg-info/dependency_links.txt
eba_binomial.egg-info/not-zip-safe
eba_binomial.egg-info/top_level.txt