Metadata-Version: 1.0
Name: eba-binomial
Version: 1.2
Summary: Gaussian and Binomial distributions
Home-page: UNKNOWN
Author: Ebisa Asfaw
Author-email: lammiyad@yahoo.com
License: UNKNOWN
Platform: UNKNOWN
